.flake8
.gitignore
.gitmodules
.pre-commit-config.yaml
.readthedocs.yaml
.rtd-environment.yml
.ruff.toml
LICENSE
MANIFEST.in
README.rst
pyproject.toml
setup.py
suncast-roadmap.md
tox.ini
docs/Makefile
docs/conf.py
docs/conf.py.rej
docs/index.rst
docs/make.bat
docs/requirements.txt
docs/images/MagFieldViewer_gui.png
docs/images/gxbox_gui.png
docs/images/pyampp_gui.png
examples/create_box.py
licenses/LICENSE.rst
licenses/README.rst
licenses/TEMPLATE_LICENSE.rst
pyampp/__init__.py
pyampp/version.py
pyampp.egg-info/PKG-INFO
pyampp.egg-info/SOURCES.txt
pyampp.egg-info/dependency_links.txt
pyampp.egg-info/entry_points.txt
pyampp.egg-info/not-zip-safe
pyampp.egg-info/requires.txt
pyampp.egg-info/top_level.txt
pyampp/data/README.rst
pyampp/data/__init__.py
pyampp/data/downloader.py
pyampp/gx_chromo/combo_model.py
pyampp/gx_chromo/decompose.py
pyampp/gx_chromo/populate_chromo.py
pyampp/gx_chromo/sav_precomputed/__init__.py
pyampp/gx_chromo/sav_precomputed/eduard_v3.sav
pyampp/gx_chromo/sav_precomputed/fontenla_b_v3.sav
pyampp/gx_chromo/sav_precomputed/fontenla_d_v3.sav
pyampp/gx_chromo/sav_precomputed/fontenla_f_v3.sav
pyampp/gx_chromo/sav_precomputed/fontenla_h_v3.sav
pyampp/gx_chromo/sav_precomputed/fontenla_p_v3.sav
pyampp/gx_chromo/sav_precomputed/fontenla_q_v3.sav
pyampp/gx_chromo/sav_precomputed/fontenla_r_v3.sav
pyampp/gx_chromo/sav_precomputed/fontenla_s_v3.sav
pyampp/gxbox/__init__.py
pyampp/gxbox/boxutils.py
pyampp/gxbox/gxampp.py
pyampp/gxbox/gxbox_factory.py
pyampp/gxbox/magfield_viewer.py
pyampp/gxbox/UI/__init__.py
pyampp/gxbox/UI/clear.svg
pyampp/gxbox/UI/gxampp.ui
pyampp/gxbox/UI/gxbox.ui
pyampp/gxbox/UI/play.svg
pyampp/gxbox/UI/refresh.svg
pyampp/gxbox/UI/save.svg
pyampp/tests/__init__.py
pyampp/tests/test_MagFieldWrapper.py
pyampp/tests/test_compare_b3d.ipynb
pyampp/tests/test_compare_b3d.py
pyampp/tests/test_magfield_viewer.py
pyampp/util/MagFieldWrapper.py
pyampp/util/compute.py
pyampp/util/config.py
pyampp/util/radio.py