Metadata-Version: 2.1
Name: pyampp
Version: 0.1.3
Summary: Automatic Model Suff
Home-page: https://github.com/suncast-org/pyAMPP
Author: The SUNCAST team
Author-email: sijie.yu@njit.edu
License: Copyright (c) 2024, suncast-org
Classifier: Development Status :: 5 - Production/Stable
Classifier: Intended Audience :: Science/Research
Classifier: License :: OSI Approved :: GNU General Public License (GPL)
Classifier: Topic :: Scientific/Engineering :: Astronomy
Requires-Python: >=3.10
Provides-Extra: dev
Provides-Extra: tests
Provides-Extra: docs
License-File: LICENSE
